dacite_ignore_case/__init__.py
dacite_ignore_case-1.0.1.dist-info/LICENSE
dacite_ignore_case-1.0.1.dist-info/METADATA
dacite_ignore_case-1.0.1.dist-info/WHEEL
dacite_ignore_case-1.0.1.dist-info/top_level.txt
dacite_ignore_case-1.0.1.dist-info/RECORD
